polarsgeoutils-0.34.25.dist-info/METADATA
polarsgeoutils-0.34.25.dist-info/WHEEL
polarsgeoutils/functions.py
polarsgeoutils/__init__.py
polarsgeoutils/__pycache__/utils.cpython-312.pyc
polarsgeoutils/__pycache__/namespace.cpython-312.pyc
polarsgeoutils/__pycache__/functions.cpython-312.pyc
polarsgeoutils/__pycache__/__init__.cpython-312.pyc
polarsgeoutils/_internal.pyi
polarsgeoutils/utils.py
polarsgeoutils/namespace.py
polarsgeoutils/polarsgeoutils.cpython-39-darwin.so
polarsgeoutils-0.34.25.dist-info/RECORD
