Metadata-Version: 2.3
Name: polarsgeoutils
Version: 0.34.25
